pydantic_env_settings/__init__.py
pydantic_env_settings/__main__.py
pydantic_env_settings-0.1.1.dist-info/LICENSE
pydantic_env_settings-0.1.1.dist-info/METADATA
pydantic_env_settings-0.1.1.dist-info/WHEEL
pydantic_env_settings-0.1.1.dist-info/RECORD
