Metadata-Version: 2.1
Name: pydantic-env-settings
Version: 0.1.1
Summary: Pydantic BaseSettings Explicit
License: MIT
Author: Jakub
Author-email: jjagielka@gmail.com
Requires-Python: >=3.10,<4.0
Classifier: License :: OSI Approved :: MIT License
Classifier: Programming Language :: Python :: 3
Classifier: Programming Language :: Python :: 3.10
Classifier: Programming Language :: Python :: 3.11
Requires-Dist: pydantic (>=1,<2)
